<?xml version="1.0" encoding="UTF-8"?><record_update table="sys_sg_view_config_element_attribute">
    <sys_sg_view_config_element_attribute action="DELETE">
        <description/>
        <name display_value="FieldValue">c2eed5c2b7321010df65f6efce11a9cf</name>
        <sys_class_name>sys_sg_view_config_element_attribute</sys_class_name>
        <sys_created_by>admin</sys_created_by>
        <sys_created_on>2024-12-15 17:42:33</sys_created_on>
        <sys_id>98a268749f6212107f441ac8c824abbf</sys_id>
        <sys_mod_count>0</sys_mod_count>
        <sys_name>c2eed5c2b7321010df65f6efce11a9cf</sys_name>
        <sys_package display_value="Fleet Management System" source="x_snc_fleet_mana_0">7025ebd49f6212107f441ac8c824ab60</sys_package>
        <sys_policy/>
        <sys_scope display_value="Fleet Management System">7025ebd49f6212107f441ac8c824ab60</sys_scope>
        <sys_update_name>sys_sg_view_config_element_attribute_98a268749f6212107f441ac8c824abbf</sys_update_name>
        <sys_updated_by>admin</sys_updated_by>
        <sys_updated_on>2024-12-15 17:42:33</sys_updated_on>
        <translated_value/>
        <value>opened_by.avatar</value>
        <view_config_element display_value="opened_by.avatar-FieldValue">58a268749f6212107f441ac8c824abbd</view_config_element>
    </sys_sg_view_config_element_attribute>
    <sys_translated_text action="DELETE" query="documentkey=98a268749f6212107f441ac8c824abbf"/>
    <sys_update_version action="INSERT_OR_UPDATE">
        <action>DELETE</action>
        <application display_value="Fleet Management System">7025ebd49f6212107f441ac8c824ab60</application>
        <file_path/>
        <instance_id>02d63469c3161e18d0265873e40131d6</instance_id>
        <instance_name>nowlearning-nlinst02283577-0001</instance_name>
        <name>sys_sg_view_config_element_attribute_98a268749f6212107f441ac8c824abbf</name>
        <payload><![CDATA[<?xml version="1.0" encoding="UTF-8"?><record_update table="sys_sg_view_config_element_attribute"><sys_sg_view_config_element_attribute action="INSERT_OR_UPDATE"><description/><name display_value="FieldValue">c2eed5c2b7321010df65f6efce11a9cf</name><sys_class_name>sys_sg_view_config_element_attribute</sys_class_name><sys_created_by>admin</sys_created_by><sys_created_on>2024-12-15 17:42:33</sys_created_on><sys_id>98a268749f6212107f441ac8c824abbf</sys_id><sys_mod_count>0</sys_mod_count><sys_name>c2eed5c2b7321010df65f6efce11a9cf</sys_name><sys_package display_value="Fleet Management System" source="x_snc_fleet_mana_0">7025ebd49f6212107f441ac8c824ab60</sys_package><sys_policy/><sys_scope display_value="Fleet Management System">7025ebd49f6212107f441ac8c824ab60</sys_scope><sys_update_name>sys_sg_view_config_element_attribute_98a268749f6212107f441ac8c824abbf</sys_update_name><sys_updated_by>admin</sys_updated_by><sys_updated_on>2024-12-15 17:42:33</sys_updated_on><translated_value/><value>opened_by.avatar</value><view_config_element display_value="opened_by.avatar-FieldValue">58a268749f6212107f441ac8c824abbd</view_config_element></sys_sg_view_config_element_attribute><sys_translated_text action="delete_multiple" query="documentkey=98a268749f6212107f441ac8c824abbf"/></record_update>]]></payload>
        <payload_hash>1265697593</payload_hash>
        <record_name>c2eed5c2b7321010df65f6efce11a9cf</record_name>
        <reverted_from/>
        <source>fc25ebd49f6212107f441ac8c824ab62</source>
        <source_table>sys_update_set</source_table>
        <state>previous</state>
        <sys_created_by>admin</sys_created_by>
        <sys_created_on>2024-12-15 17:42:33</sys_created_on>
        <sys_id>58a268749f6212107f441ac8c824abc1</sys_id>
        <sys_mod_count>0</sys_mod_count>
        <sys_recorded_at>193cb6a2cfa0000001</sys_recorded_at>
        <sys_updated_by>admin</sys_updated_by>
        <sys_updated_on>2024-12-15 17:42:33</sys_updated_on>
        <type>Card element attribute</type>
        <update_guid>5ca26874f96212109825b362bc81e7c0</update_guid>
        <update_guid_history>5ca26874f96212109825b362bc81e7c0:1265697593</update_guid_history>
    </sys_update_version>
    <sys_metadata_delete action="INSERT_OR_UPDATE">
        <sys_audit_delete/>
        <sys_class_name>sys_metadata_delete</sys_class_name>
        <sys_created_by>admin</sys_created_by>
        <sys_created_on>2024-12-18 07:23:28</sys_created_on>
        <sys_db_object display_value="" name="sys_sg_view_config_element_attribute">sys_sg_view_config_element_attribute</sys_db_object>
        <sys_id>27e0024751174153a8a9d551cdfa09f9</sys_id>
        <sys_metadata>98a268749f6212107f441ac8c824abbf</sys_metadata>
        <sys_mod_count>0</sys_mod_count>
        <sys_name>c2eed5c2b7321010df65f6efce11a9cf</sys_name>
        <sys_package display_value="Fleet Management System" source="x_snc_fleet_mana_0">7025ebd49f6212107f441ac8c824ab60</sys_package>
        <sys_parent/>
        <sys_policy/>
        <sys_scope display_value="Fleet Management System">7025ebd49f6212107f441ac8c824ab60</sys_scope>
        <sys_scope_delete display_value="">140f9742cb024c38ac5b3e9b6f42d040</sys_scope_delete>
        <sys_update_name>sys_sg_view_config_element_attribute_98a268749f6212107f441ac8c824abbf</sys_update_name>
        <sys_update_version display_value="sys_sg_view_config_element_attribute_98a268749f6212107f441ac8c824abbf">58a268749f6212107f441ac8c824abc1</sys_update_version>
        <sys_updated_by>admin</sys_updated_by>
        <sys_updated_on>2024-12-18 07:23:28</sys_updated_on>
    </sys_metadata_delete>
</record_update>
